quotes_api/__init__.py
quotes_api/client.py
quotes_api/config.py
quotes_api/exceptions.py
quotes_api/vcr.py
quotes_api-0.1.1.dist-info/LICENSE
quotes_api-0.1.1.dist-info/WHEEL
quotes_api-0.1.1.dist-info/METADATA
quotes_api-0.1.1.dist-info/RECORD
