Metadata-Version: 2.1
Name: quotes-api
Version: 0.1.1
Summary: 
Author: guilhermevbeira
Author-email: guilherme.vieira.beira@gmail.com
Requires-Python: >=3.7,<4.0
Classifier: Programming Language :: Python :: 3
Classifier: Programming Language :: Python :: 3.7
Requires-Dist: requests (>=2.22,<3.0)
